cubao_pypi_example/__init__.py
cubao_pypi_example/__main__.py
cubao_pypi_example/package_data.dat
cubao_pypi_example/simple.py
cubao_pypi_example-0.0.3.dist-info/LICENSE.txt
cubao_pypi_example-0.0.3.dist-info/METADATA
cubao_pypi_example-0.0.3.dist-info/WHEEL
cubao_pypi_example-0.0.3.dist-info/top_level.txt
cubao_pypi_example-0.0.3.dist-info/RECORD
